clingo/clingo.h
clingo/configuration.py
clingo/backend.py
clingo/solving.py
clingo/_internal.py
clingo/util.py
clingo/symbolic_atoms.py
clingo/control.py
clingo/__init__.py
clingo/symbol.py
clingo/core.py
clingo/_clingo.cpython-38-darwin.so
clingo/application.py
clingo/theory.py
clingo/clingo.hh
clingo/ast.py
clingo/py.typed
clingo/statistics.py
clingo/theory_atoms.py
clingo/script.py
clingo/propagator.py
clingo/__main__.py
clingo-5.8.0.dist-info/LICENSE.md
clingo-5.8.0.dist-info/RECORD
clingo-5.8.0.dist-info/WHEEL
clingo-5.8.0.dist-info/top_level.txt
clingo-5.8.0.dist-info/METADATA
