Metadata-Version: 2.1
Name: clingo
Version: 5.8.0
Summary: CFFI-based bindings to the clingo solver.
Home-page: https://github.com/potassco/clingo
Author: Roland Kaminski
Author-email: kaminski@cs.uni-potsdam.de
License: MIT
Platform: UNKNOWN
Requires-Python: >=3.6
License-File: LICENSE.md
Requires-Dist: cffi
